{
    "w1_t": 25.0,
    "bme280_t": 23.95,
    "bme280_p": 745.8,
    "bme280_h": 10.32,
    "fc_t": -11.22,
    "fc_h": 0.79,
    "fc_p": 751.04,
    "time": 1582933805,
    "temp_direction": 0,
    "forecast": {
        "now_summary": "Ясно",
        "now_icon": "clear-night",
        "now_temperature": -11.22,
        "now_humidity": 0.79,
        "now_pressure": 751.04,
        "now_windSpeed": 2.16,
        "today_summary": "Без осадков в течение всей недели.",
        "today_icon": "clear-day",
        "tomorrow_summary": "Сильная облачность в течение всего дня.",
        "tomorrow_icon": "cloudy",
        "tomorrow_temperatureMax": -8.65,
        "tomorrow_temperatureMin": -16.22,
        "tomorrow_humidity": 0.79,
        "tomorrow_pressure": 746.01,
        "tomorrow_windSpeed": 1.44,
        "now_precipType": null,
        "tomorrow_precipType": "snow"
    }
}