{
    "w1_t": -12.38,
    "bme280_t": 22.39,
    "bme280_p": 741.12,
    "bme280_h": 11.44,
    "fc_t": -11.92,
    "fc_h": 0.86,
    "fc_p": 746.24,
    "time": 1582749605,
    "temp_direction": -1,
    "forecast": {
        "now_summary": "Сильная Облачность",
        "now_icon": "cloudy",
        "now_temperature": -11.92,
        "now_humidity": 0.86,
        "now_pressure": 746.24,
        "now_windSpeed": 2.87,
        "today_summary": "Возможен незначительный снег в понедельник.",
        "today_icon": "snow",
        "tomorrow_summary": "Туман утром.",
        "tomorrow_icon": "fog",
        "tomorrow_temperatureMax": -5.24,
        "tomorrow_temperatureMin": -11.93,
        "tomorrow_humidity": 0.82,
        "tomorrow_pressure": 746.69,
        "tomorrow_windSpeed": 3.04,
        "now_precipType": "snow",
        "tomorrow_precipType": "snow"
    }
}