{
    "w1_t": -7.19,
    "bme280_t": 23.54,
    "bme280_p": 741.25,
    "bme280_h": 14.04,
    "fc_t": -10,
    "fc_h": 0.91,
    "fc_p": 746.76,
    "time": 1582788006,
    "temp_direction": -1,
    "forecast": {
        "now_summary": "Сильная Облачность",
        "now_icon": "cloudy",
        "now_temperature": -10,
        "now_humidity": 0.91,
        "now_pressure": 746.76,
        "now_windSpeed": 2.26,
        "today_summary": "Возможен незначительный снег в среду.",
        "today_icon": "snow",
        "tomorrow_summary": "Ясно в течение всего дня.",
        "tomorrow_icon": "clear-day",
        "tomorrow_temperatureMax": -3.83,
        "tomorrow_temperatureMin": -11.64,
        "tomorrow_humidity": 0.73,
        "tomorrow_pressure": 751.04,
        "tomorrow_windSpeed": 3.14,
        "now_precipType": "snow",
        "tomorrow_precipType": "snow"
    }
}